amcrest_api/__init__.py
amcrest_api/__main__.py
amcrest_api/camera.py
amcrest_api/config.py
amcrest_api/const.py
amcrest_api/error.py
amcrest_api/event.py
amcrest_api/imaging.py
amcrest_api/ptz.py
amcrest_api/storage.py
amcrest_api/utils.py
amcrest_api-0.1.6.dist-info/METADATA
amcrest_api-0.1.6.dist-info/WHEEL
amcrest_api-0.1.6.dist-info/licenses/LICENSE
amcrest_api-0.1.6.dist-info/RECORD
