Metadata-Version: 2.4
Name: amcrest_api
Version: 0.1.6
Summary: Python Wrapper for Amcrest API v3.26 or greater.
Author-email: Benjamin Pearce <amcrest_api@bcpearce.com>
License-Expression: MIT
License-File: LICENSE
Requires-Python: >=3.9
Requires-Dist: httpx>=0.27.2
Requires-Dist: yarl>=1.15.2
